spartan/__init__.py
spartan/spartan.py
spartan/backend/__init__.py
spartan/backend/cpu_backend/__init__.py
spartan/backend/cpu_backend/common.py
spartan/backend/cpu_backend/tensor.py
spartan/backend/gpu_backend/__init__.py
spartan/backend/gpu_backend/common.py
spartan/backend/gpu_backend/tensor.py
spartan/model/__init__.py
spartan/model/_model.py
spartan/model/beatgan/BeatGAN_CNN.py
spartan/model/beatgan/BeatGAN_RNN.py
spartan/model/beatgan/__init__.py
spartan/model/beatgan/metric.py
spartan/model/beatgan/preprocess.py
spartan/model/beatlex/Beatlex.py
spartan/model/beatlex/__init__.py
spartan/model/eaglemine/__init__.py
spartan/model/eaglemine/eaglemine.py
spartan/model/eaglemine/eaglemine_model.py
spartan/model/eaglemine/run_eaglemine.py
spartan/model/eaglemine/run_feature2histogram.py
spartan/model/eaglemine/run_graph2histogram.py
spartan/model/eaglemine/run_views_viz.py
spartan/model/eaglemine/run_waterleveltree.py
spartan/model/eaglemine/core/__init__.py
spartan/model/eaglemine/core/leveltree.py
spartan/model/eaglemine/desc/__init__.py
spartan/model/eaglemine/desc/discrete_gaussian.py
spartan/model/eaglemine/desc/dtmnorm.py
spartan/model/eaglemine/desc/dtmnorm_describe.py
spartan/model/eaglemine/desc/gaussian_describe.py
spartan/model/eaglemine/desc/norm_extras.py
spartan/model/eaglemine/desc/normal_gaussian.py
spartan/model/eaglemine/desc/statistic_hypothesis_test.py
spartan/model/eaglemine/desc/statistic_hypothesis_test_truncate.py
spartan/model/eaglemine/desc/truncate_norm_gof.py
spartan/model/eaglemine/desc/truncated_gaussian.py
spartan/model/eaglemine/tools/__init__.py
spartan/model/eaglemine/tools/graph.py
spartan/model/eaglemine/tools/histogram_heuristic_generator.py
spartan/model/eaglemine/utils/__init__.py
spartan/model/eaglemine/utils/loader.py
spartan/model/eaglemine/utils/mdlbase.py
spartan/model/eaglemine/utils/ploter.py
spartan/model/eaglemine/utils/ploter_aux.py
spartan/model/eigenpulse/EigenPulse.py
spartan/model/eigenpulse/SinglePassPCA.py
spartan2-0.0.2.dist-info/LICENSE
spartan2-0.0.2.dist-info/METADATA
spartan2-0.0.2.dist-info/WHEEL
spartan2-0.0.2.dist-info/top_level.txt
spartan2-0.0.2.dist-info/RECORD
