Metadata-Version: 2.1
Name: spartan2
Version: 0.0.2
Summary: collection of data mining algorithms on big graphs and time series
Home-page: https://github.com/BGT-M/spartan2
Author: Shenghua Liu, Houquan Zhou, Quan Ding, Jiabao Zhang, Xin Zhao, Siwei Zeng,etc
Author-email: liu.shengh@foxmail.com
License: UNKNOWN
Platform: UNKNOWN
Classifier: Programming Language :: Python :: 3
Classifier: License :: OSI Approved :: MIT License
Classifier: Operating System :: OS Independent
Requires-Python: >=3.6
Requires-Dist: numpy
Requires-Dist: scipy
Requires-Dist: networkx
Requires-Dist: matplotlib
Requires-Dist: statsmodels
Requires-Dist: pomegranate
Requires-Dist: scikit-learn
Requires-Dist: scikit-image
Requires-Dist: sparse
Requires-Dist: ipdb
